LICENSE
MANIFEST.in
README
setup.py
geodjango_timezones.egg-info/PKG-INFO
geodjango_timezones.egg-info/SOURCES.txt
geodjango_timezones.egg-info/dependency_links.txt
geodjango_timezones.egg-info/top_level.txt
timezones/__init__.py
timezones/admin.py
timezones/exceptions.py
timezones/forms.py
timezones/models.py
timezones/tests.py
timezones/utils.py
timezones/fixtures/timezones.json
timezones/management/__init__.py
timezones/management/commands/__init__.py
timezones/management/commands/load_timezones.py
timezones/management/commands/prep_fixture.py
timezones/migrations/0001_initial.py
timezones/migrations/__init__.py
timezones/south_migrations/0001_initial.py
timezones/south_migrations/__init__.py