Metadata-Version: 1.1
Name: geodjango-timezones
Version: 1.0
Summary: Models to store and scripts to load timezone shapefiles to be usable inside a GeoDjango application.
Home-page: https://github.com/adamfast/geodjango-timezones
Author: Adam Fast
Author-email: adamfast@gmail.com
License: BSD
Keywords: timezones gis
Platform: UNKNOWN
Classifier: Development Status :: 5 - Production/Stable
Classifier: Intended Audience :: Developers
Classifier: License :: OSI Approved :: BSD License
Classifier: Programming Language :: Python :: 2.7
